{
	"name": "opt-pilot",
	"dvar-bounds": {
		"IBF": [ 200, 500 ],
		"IM": [ 170, 260 ],
		"GPHASE": [ -30, 0 ],
		"FWHM": [ 1.5, 10 ],
		"KQ1": [ -8, 8 ],
		"KQ2": [ -8, 8 ],
		"KQ3": [ -8, 8 ],
		"KQ4": [ -8, 8 ]
	}
	,
	"constraints": [
		"fabs(statVariableAt('rms_x',16.5))<1.0e-1",
		"fabs(statVariableAt('rms_y',16.5))<1.0e-1"
	]
	,
	"solutions": [
	{
		"ID": 0,
		"obj":
		{
			"EMITX1": 0.000230697,
			"EMITX2": 0.00127568,
			"RMSS1": 0.00137651,
			"RMSS2": 0.00143676
		}
		,
		"dvar":
		{
			"IBF": 433.025,
			"IM": 217.804,
			"GPHASE": -6.73076,
			"FWHM": 5.79475,
			"KQ1": -2.096,
			"KQ2": -2.20754,
			"KQ3": 2.87752,
			"KQ4": 0.595402
		}
	}
	,
	{
		"ID": 2,
		"obj":
		{
			"EMITX1": 0.000111919,
			"EMITX2": 0.000314648,
			"RMSS1": 0.00147025,
			"RMSS2": 0.00147558
		}
		,
		"dvar":
		{
			"IBF": 330.213,
			"IM": 240.049,
			"GPHASE": -8.0053,
			"FWHM": 6.24304,
			"KQ1": -3.2098,
			"KQ2": -2.6269,
			"KQ3": 7.38451,
			"KQ4": -7.39095
		}
	}
	,
	{
		"ID": 3,
		"obj":
		{
			"EMITX1": 0.000405755,
			"EMITX2": 0.00138398,
			"RMSS1": 0.00113313,
			"RMSS2": 0.00127275
		}
		,
		"dvar":
		{
			"IBF": 309.703,
			"IM": 218.594,
			"GPHASE": -2.75893,
			"FWHM": 2.81285,
			"KQ1": 0.902073,
			"KQ2": -3.37089,
			"KQ3": -1.88567,
			"KQ4": 7.11589
		}
	}
	,
	{
		"ID": 4,
		"obj":
		{
			"EMITX1": 0.000111919,
			"EMITX2": 0.000314648,
			"RMSS1": 0.00147025,
			"RMSS2": 0.00147558
		}
		,
		"dvar":
		{
			"IBF": 330.213,
			"IM": 240.049,
			"GPHASE": -8.0053,
			"FWHM": 6.24304,
			"KQ1": -3.2098,
			"KQ2": -2.6269,
			"KQ3": 7.38451,
			"KQ4": -7.39095
		}
	}
	,
	{
		"ID": 6,
		"obj":
		{
			"EMITX1": 0.000170672,
			"EMITX2": 0.000279343,
			"RMSS1": 0.00130826,
			"RMSS2": 0.00123314
		}
		,
		"dvar":
		{
			"IBF": 403.601,
			"IM": 228.799,
			"GPHASE": -1.47888,
			"FWHM": 3.13222,
			"KQ1": 0.15906,
			"KQ2": 0.796556,
			"KQ3": -4.08857,
			"KQ4": 4.97952
		}
	}
	,
	{
		"ID": 7,
		"obj":
		{
			"EMITX1": 0.000403703,
			"EMITX2": 0.000802965,
			"RMSS1": 0.00223855,
			"RMSS2": 0.00105942
		}
		,
		"dvar":
		{
			"IBF": 311.88,
			"IM": 246.425,
			"GPHASE": -4.45279,
			"FWHM": 2.41002,
			"KQ1": -1.43327,
			"KQ2": -4.71223,
			"KQ3": 1.25089,
			"KQ4": -1.8874
		}
	}
	,
	{
		"ID": 14,
		"obj":
		{
			"EMITX1": 0.000285789,
			"EMITX2": 0.000554535,
			"RMSS1": 0.00286973,
			"RMSS2": 0.00123047
		}
		,
		"dvar":
		{
			"IBF": 395.637,
			"IM": 248.822,
			"GPHASE": -5.66145,
			"FWHM": 5.14467,
			"KQ1": -2.72104,
			"KQ2": -1.40729,
			"KQ3": 0.541013,
			"KQ4": -2.60551
		}
	}
	,
	{
		"ID": 16,
		"obj":
		{
			"EMITX1": 0.000351645,
			"EMITX2": 0.000821772,
			"RMSS1": 0.00489185,
			"RMSS2": 0.00104752
		}
		,
		"dvar":
		{
			"IBF": 310.721,
			"IM": 233.057,
			"GPHASE": -1.34612,
			"FWHM": 4.91155,
			"KQ1": -0.969328,
			"KQ2": -3.14718,
			"KQ3": -5.74515,
			"KQ4": -3.56412
		}
	}
	,
	{
		"ID": 19,
		"obj":
		{
			"EMITX1": 0.000496486,
			"EMITX2": 0.000925266,
			"RMSS1": 0.0022814,
			"RMSS2": 0.00113165
		}
		,
		"dvar":
		{
			"IBF": 263.372,
			"IM": 247.928,
			"GPHASE": -3.40832,
			"FWHM": 2.53774,
			"KQ1": -2.77811,
			"KQ2": -4.77465,
			"KQ3": 3.0483,
			"KQ4": -2.44193
		}
	}
	,
	{
		"ID": 20,
		"obj":
		{
			"EMITX1": 0.000678185,
			"EMITX2": 0.00215899,
			"RMSS1": 0.00123856,
			"RMSS2": 0.00124861
		}
		,
		"dvar":
		{
			"IBF": 497.209,
			"IM": 219.73,
			"GPHASE": -3.60156,
			"FWHM": 2.39626,
			"KQ1": -2.62537,
			"KQ2": -2.11771,
			"KQ3": -5.70612,
			"KQ4": 2.74915
		}
	}
	,
	{
		"ID": 21,
		"obj":
		{
			"EMITX1": 0.000405755,
			"EMITX2": 0.00138398,
			"RMSS1": 0.00113313,
			"RMSS2": 0.00127275
		}
		,
		"dvar":
		{
			"IBF": 309.703,
			"IM": 218.594,
			"GPHASE": -2.75893,
			"FWHM": 2.81285,
			"KQ1": 0.902073,
			"KQ2": -3.37089,
			"KQ3": -1.88567,
			"KQ4": 7.11589
		}
	}
	,
	{
		"ID": 22,
		"obj":
		{
			"EMITX1": 0.000166136,
			"EMITX2": 0.000594562,
			"RMSS1": 0.00149797,
			"RMSS2": 0.00143253
		}
		,
		"dvar":
		{
			"IBF": 423.398,
			"IM": 226.565,
			"GPHASE": -6.15411,
			"FWHM": 7.28911,
			"KQ1": 1.93594,
			"KQ2": -0.390115,
			"KQ3": 5.8731,
			"KQ4": -3.83175
		}
	}
	,
	{
		"ID": 23,
		"obj":
		{
			"EMITX1": 0.000166136,
			"EMITX2": 0.000594562,
			"RMSS1": 0.00149797,
			"RMSS2": 0.00143253
		}
		,
		"dvar":
		{
			"IBF": 423.398,
			"IM": 226.565,
			"GPHASE": -6.15411,
			"FWHM": 7.28911,
			"KQ1": 1.93594,
			"KQ2": -0.390115,
			"KQ3": 5.8731,
			"KQ4": -3.83175
		}
	}
	,
	{
		"ID": 24,
		"obj":
		{
			"EMITX1": 0.000166136,
			"EMITX2": 0.000594562,
			"RMSS1": 0.00149797,
			"RMSS2": 0.00143253
		}
		,
		"dvar":
		{
			"IBF": 423.398,
			"IM": 226.565,
			"GPHASE": -6.15411,
			"FWHM": 7.28911,
			"KQ1": 1.93594,
			"KQ2": -0.390115,
			"KQ3": 5.8731,
			"KQ4": -3.83175
		}
	}
	,
	{
		"ID": 25,
		"obj":
		{
			"EMITX1": 0.000532136,
			"EMITX2": 0.000865499,
			"RMSS1": 0.00351066,
			"RMSS2": 0.00105455
		}
		,
		"dvar":
		{
			"IBF": 311.88,
			"IM": 246.425,
			"GPHASE": -4.45279,
			"FWHM": 2.41002,
			"KQ1": -3.45461,
			"KQ2": -4.71223,
			"KQ3": 1.25089,
			"KQ4": -1.8874
		}
	}
	,
	{
		"ID": 27,
		"obj":
		{
			"EMITX1": 0.000923947,
			"EMITX2": 0.0030596,
			"RMSS1": 0.00118481,
			"RMSS2": 0.00144975
		}
		,
		"dvar":
		{
			"IBF": 359.7,
			"IM": 227.694,
			"GPHASE": -8.5904,
			"FWHM": 2.54237,
			"KQ1": 2.0882,
			"KQ2": -0.864941,
			"KQ3": -0.548992,
			"KQ4": -5.81305
		}
	}
	,
	{
		"ID": 29,
		"obj":
		{
			"EMITX1": 0.000240196,
			"EMITX2": 0.000363193,
			"RMSS1": 0.0014006,
			"RMSS2": 0.00121086
		}
		,
		"dvar":
		{
			"IBF": 259.388,
			"IM": 237.165,
			"GPHASE": -6.4103,
			"FWHM": 5.13327,
			"KQ1": 4.43543,
			"KQ2": 4.54695,
			"KQ3": -4.4884,
			"KQ4": 0.00650031
		}
	}
	,
	{
		"ID": 30,
		"obj":
		{
			"EMITX1": 0.000307775,
			"EMITX2": 0.000597586,
			"RMSS1": 0.0011447,
			"RMSS2": 0.00128517
		}
		,
		"dvar":
		{
			"IBF": 357.18,
			"IM": 214.897,
			"GPHASE": -7.69535,
			"FWHM": 2.07062,
			"KQ1": -2.63568,
			"KQ2": 5.0327,
			"KQ3": 1.61431,
			"KQ4": -3.57638
		}
	}
	,
	{
		"ID": 31,
		"obj":
		{
			"EMITX1": 0.000188847,
			"EMITX2": 0.000355532,
			"RMSS1": 0.00173941,
			"RMSS2": 0.00152311
		}
		,
		"dvar":
		{
			"IBF": 484.754,
			"IM": 226.393,
			"GPHASE": -0.384713,
			"FWHM": 8.77105,
			"KQ1": 3.72077,
			"KQ2": -4.45205,
			"KQ3": 7.43893,
			"KQ4": -5.20699
		}
	}
	,
	{
		"ID": 34,
		"obj":
		{
			"EMITX1": 0.00044736,
			"EMITX2": 0.00174133,
			"RMSS1": 0.00133233,
			"RMSS2": 0.00140441
		}
		,
		"dvar":
		{
			"IBF": 311.333,
			"IM": 210.86,
			"GPHASE": -4.93196,
			"FWHM": 2.82142,
			"KQ1": 1.42194,
			"KQ2": -3.12983,
			"KQ3": -0.810109,
			"KQ4": 8.6619
		}
	}
	,
	{
		"ID": 35,
		"obj":
		{
			"EMITX1": 0.000634732,
			"EMITX2": 0.000910531,
			"RMSS1": 0.0013996,
			"RMSS2": 0.00129528
		}
		,
		"dvar":
		{
			"IBF": 479.519,
			"IM": 203.053,
			"GPHASE": -10.0575,
			"FWHM": 3.10304,
			"KQ1": 7.69475,
			"KQ2": -5.05992,
			"KQ3": 3.57689,
			"KQ4": -3.10863
		}
	}
	,
	{
		"ID": 37,
		"obj":
		{
			"EMITX1": 0.000270427,
			"EMITX2": 0.00078157,
			"RMSS1": 0.00118308,
			"RMSS2": 0.00120158
		}
		,
		"dvar":
		{
			"IBF": 342.241,
			"IM": 219.68,
			"GPHASE": -1.16563,
			"FWHM": 3.07144,
			"KQ1": 0.398251,
			"KQ2": -2.96464,
			"KQ3": -1.31959,
			"KQ4": 7.35289
		}
	}
	,
	{
		"ID": 38,
		"obj":
		{
			"EMITX1": 0.000135994,
			"EMITX2": 0.000300794,
			"RMSS1": 0.00131315,
			"RMSS2": 0.00115759
		}
		,
		"dvar":
		{
			"IBF": 452.474,
			"IM": 228.172,
			"GPHASE": -6.44902,
			"FWHM": 3.14434,
			"KQ1": -0.876884,
			"KQ2": 0.425358,
			"KQ3": -3.88636,
			"KQ4": 7.19488
		}
	}
	,
	{
		"ID": 39,
		"obj":
		{
			"EMITX1": 0.000170672,
			"EMITX2": 0.000279343,
			"RMSS1": 0.00130826,
			"RMSS2": 0.00123314
		}
		,
		"dvar":
		{
			"IBF": 403.601,
			"IM": 228.799,
			"GPHASE": -1.47888,
			"FWHM": 3.13222,
			"KQ1": 0.15906,
			"KQ2": 0.796556,
			"KQ3": -4.08857,
			"KQ4": 4.97952
		}
	}
	,
	{
		"ID": 41,
		"obj":
		{
			"EMITX1": 0.000305812,
			"EMITX2": 0.00130328,
			"RMSS1": 0.0014418,
			"RMSS2": 0.00117908
		}
		,
		"dvar":
		{
			"IBF": 328.025,
			"IM": 230.434,
			"GPHASE": -8.85322,
			"FWHM": 4.44333,
			"KQ1": -1.19045,
			"KQ2": -0.0885051,
			"KQ3": -4.10573,
			"KQ4": -4.76376
		}
	}
	,
	{
		"ID": 43,
		"obj":
		{
			"EMITX1": 0.000369802,
			"EMITX2": 0.00121435,
			"RMSS1": 0.00116964,
			"RMSS2": 0.00128794
		}
		,
		"dvar":
		{
			"IBF": 218.908,
			"IM": 224.217,
			"GPHASE": -8.21976,
			"FWHM": 2.73945,
			"KQ1": -2.73859,
			"KQ2": 0.991866,
			"KQ3": 2.33494,
			"KQ4": -4.31325
		}
	}
	,
	{
		"ID": 44,
		"obj":
		{
			"EMITX1": 0.000532136,
			"EMITX2": 0.000865499,
			"RMSS1": 0.00351066,
			"RMSS2": 0.00105455
		}
		,
		"dvar":
		{
			"IBF": 311.88,
			"IM": 246.425,
			"GPHASE": -4.45279,
			"FWHM": 2.41002,
			"KQ1": -3.45461,
			"KQ2": -4.71223,
			"KQ3": 1.25089,
			"KQ4": -1.8874
		}
	}
	,
	{
		"ID": 48,
		"obj":
		{
			"EMITX1": 0.000129384,
			"EMITX2": 0.000917332,
			"RMSS1": 0.0015991,
			"RMSS2": 0.00161201
		}
		,
		"dvar":
		{
			"IBF": 378.282,
			"IM": 224.882,
			"GPHASE": -11.4069,
			"FWHM": 10.6474,
			"KQ1": -3.82484,
			"KQ2": 3.53134,
			"KQ3": -7.70977,
			"KQ4": -1.48761
		}
	}
	,
	{
		"ID": 51,
		"obj":
		{
			"EMITX1": 0.000307775,
			"EMITX2": 0.000597586,
			"RMSS1": 0.0011447,
			"RMSS2": 0.00128517
		}
		,
		"dvar":
		{
			"IBF": 357.18,
			"IM": 214.897,
			"GPHASE": -7.69535,
			"FWHM": 2.07062,
			"KQ1": -2.63568,
			"KQ2": 5.0327,
			"KQ3": 1.61431,
			"KQ4": -3.57638
		}
	}
	,
	{
		"ID": 53,
		"obj":
		{
			"EMITX1": 0.000341212,
			"EMITX2": 0.000631748,
			"RMSS1": 0.00124242,
			"RMSS2": 0.00115021
		}
		,
		"dvar":
		{
			"IBF": 267.182,
			"IM": 232.418,
			"GPHASE": -8.62302,
			"FWHM": 3.73979,
			"KQ1": -7.30164,
			"KQ2": 6.74059,
			"KQ3": 5.54984,
			"KQ4": -5.45537
		}
	}
	,
	{
		"ID": 55,
		"obj":
		{
			"EMITX1": 0.000532136,
			"EMITX2": 0.000865499,
			"RMSS1": 0.00351066,
			"RMSS2": 0.00105455
		}
		,
		"dvar":
		{
			"IBF": 311.88,
			"IM": 246.425,
			"GPHASE": -4.45279,
			"FWHM": 2.41002,
			"KQ1": -3.45461,
			"KQ2": -4.71223,
			"KQ3": 1.25089,
			"KQ4": -1.8874
		}
	}
	,
	{
		"ID": 56,
		"obj":
		{
			"EMITX1": 0.000178008,
			"EMITX2": 0.000865071,
			"RMSS1": 0.0011394,
			"RMSS2": 0.00117016
		}
		,
		"dvar":
		{
			"IBF": 467.948,
			"IM": 220.693,
			"GPHASE": -6.36096,
			"FWHM": 1.77761,
			"KQ1": 7.36874,
			"KQ2": -2.4568,
			"KQ3": -0.658813,
			"KQ4": -0.517806
		}
	}
	,
	{
		"ID": 58,
		"obj":
		{
			"EMITX1": 0.000532136,
			"EMITX2": 0.000865499,
			"RMSS1": 0.00351066,
			"RMSS2": 0.00105455
		}
		,
		"dvar":
		{
			"IBF": 311.88,
			"IM": 246.425,
			"GPHASE": -4.45279,
			"FWHM": 2.41002,
			"KQ1": -3.45461,
			"KQ2": -4.71223,
			"KQ3": 1.25089,
			"KQ4": -1.8874
		}
	}
	,
	{
		"ID": 67,
		"obj":
		{
			"EMITX1": 0.000405755,
			"EMITX2": 0.00138398,
			"RMSS1": 0.00113313,
			"RMSS2": 0.00127275
		}
		,
		"dvar":
		{
			"IBF": 309.703,
			"IM": 218.594,
			"GPHASE": -2.75893,
			"FWHM": 2.81285,
			"KQ1": 0.902073,
			"KQ2": -3.37089,
			"KQ3": -1.88567,
			"KQ4": 7.11589
		}
	}
	,
	{
		"ID": 69,
		"obj":
		{
			"EMITX1": 0.000405755,
			"EMITX2": 0.00138398,
			"RMSS1": 0.00113313,
			"RMSS2": 0.00127275
		}
		,
		"dvar":
		{
			"IBF": 309.703,
			"IM": 218.594,
			"GPHASE": -2.75893,
			"FWHM": 2.81285,
			"KQ1": 0.902073,
			"KQ2": -3.37089,
			"KQ3": -1.88567,
			"KQ4": 7.11589
		}
	}
	,
	{
		"ID": 72,
		"obj":
		{
			"EMITX1": 0.000250818,
			"EMITX2": 0.00104312,
			"RMSS1": 0.00125647,
			"RMSS2": 0.00105365
		}
		,
		"dvar":
		{
			"IBF": 373.796,
			"IM": 227.722,
			"GPHASE": -3.13072,
			"FWHM": 1.84611,
			"KQ1": -1.52436,
			"KQ2": -1.89135,
			"KQ3": -1.60287,
			"KQ4": -1.37227
		}
	}
	,
	{
		"ID": 73,
		"obj":
		{
			"EMITX1": 0.000239648,
			"EMITX2": 0.000972882,
			"RMSS1": 0.00162221,
			"RMSS2": 0.00106758
		}
		,
		"dvar":
		{
			"IBF": 364.924,
			"IM": 229.961,
			"GPHASE": -7.00764,
			"FWHM": 2.50556,
			"KQ1": -2.29166,
			"KQ2": 1.34466,
			"KQ3": -3.3248,
			"KQ4": -6.08486
		}
	}
	,
	{
		"ID": 79,
		"obj":
		{
			"EMITX1": 0.000120467,
			"EMITX2": 0.000742887,
			"RMSS1": 0.0015557,
			"RMSS2": 0.00144299
		}
		,
		"dvar":
		{
			"IBF": 239.84,
			"IM": 240.621,
			"GPHASE": -10.2479,
			"FWHM": 8.17613,
			"KQ1": -1.43827,
			"KQ2": -0.522985,
			"KQ3": -3.33792,
			"KQ4": 1.46091
		}
	}
	,
	{
		"ID": 82,
		"obj":
		{
			"EMITX1": 0.00025863,
			"EMITX2": 0.000502692,
			"RMSS1": 0.00141463,
			"RMSS2": 0.00140007
		}
		,
		"dvar":
		{
			"IBF": 209.176,
			"IM": 227.131,
			"GPHASE": -4.42323,
			"FWHM": 8.40005,
			"KQ1": -8.16803,
			"KQ2": 5.72908,
			"KQ3": -6.84303,
			"KQ4": -1.10453
		}
	}
	,
	{
		"ID": 88,
		"obj":
		{
			"EMITX1": 0.000476186,
			"EMITX2": 0.00120425,
			"RMSS1": 0.00140375,
			"RMSS2": 0.00149555
		}
		,
		"dvar":
		{
			"IBF": 434.728,
			"IM": 212.281,
			"GPHASE": -3.78051,
			"FWHM": 7.57302,
			"KQ1": -7.02304,
			"KQ2": -1.98379,
			"KQ3": 6.14809,
			"KQ4": -5.07756
		}
	}
	,
	{
		"ID": 94,
		"obj":
		{
			"EMITX1": 0.000243625,
			"EMITX2": 0.00105755,
			"RMSS1": 0.00143871,
			"RMSS2": 0.00112814
		}
		,
		"dvar":
		{
			"IBF": 254.623,
			"IM": 233.748,
			"GPHASE": -7.07606,
			"FWHM": 4.32323,
			"KQ1": -2.02372,
			"KQ2": -0.835481,
			"KQ3": -3.76954,
			"KQ4": -2.3026
		}
	}
	,
	{
		"ID": 101,
		"obj":
		{
			"EMITX1": 0.000127332,
			"EMITX2": 0.000371316,
			"RMSS1": 0.00161819,
			"RMSS2": 0.00162809
		}
		,
		"dvar":
		{
			"IBF": 336.098,
			"IM": 243.727,
			"GPHASE": -6.7912,
			"FWHM": 8.61907,
			"KQ1": -5.06205,
			"KQ2": 3.94693,
			"KQ3": 3.10216,
			"KQ4": -6.01456
		}
	}
	,
	{
		"ID": 103,
		"obj":
		{
			"EMITX1": 0.00050559,
			"EMITX2": 0.000790361,
			"RMSS1": 0.00381113,
			"RMSS2": 0.000996728
		}
		,
		"dvar":
		{
			"IBF": 252.291,
			"IM": 241.38,
			"GPHASE": -0.401161,
			"FWHM": 2.00359,
			"KQ1": -5.18034,
			"KQ2": -4.79501,
			"KQ3": 3.46059,
			"KQ4": -3.66856
		}
	}
	,
	{
		"ID": 108,
		"obj":
		{
			"EMITX1": 0.000678185,
			"EMITX2": 0.00215899,
			"RMSS1": 0.00123856,
			"RMSS2": 0.00124861
		}
		,
		"dvar":
		{
			"IBF": 497.209,
			"IM": 219.73,
			"GPHASE": -3.60156,
			"FWHM": 2.39626,
			"KQ1": -2.62537,
			"KQ2": -2.11771,
			"KQ3": -5.70612,
			"KQ4": 2.74915
		}
	}
	,
	{
		"ID": 143,
		"obj":
		{
			"EMITX1": 0.00128859,
			"EMITX2": 0.00431762,
			"RMSS1": 0.00117526,
			"RMSS2": 0.00175213
		}
		,
		"dvar":
		{
			"IBF": 220.123,
			"IM": 228.19,
			"GPHASE": -0.241865,
			"FWHM": 2.58916,
			"KQ1": -7.63891,
			"KQ2": 6.0191,
			"KQ3": -3.02737,
			"KQ4": 2.13541
		}
	}
	,
	{
		"ID": 158,
		"obj":
		{
			"EMITX1": 0.00025431,
			"EMITX2": 0.00131408,
			"RMSS1": 0.00130154,
			"RMSS2": 0.00131878
		}
		,
		"dvar":
		{
			"IBF": 466.867,
			"IM": 217.246,
			"GPHASE": -1.15673,
			"FWHM": 3.81728,
			"KQ1": -6.46649,
			"KQ2": 5.02361,
			"KQ3": -0.750261,
			"KQ4": -1.93254
		}
	}
	,
	{
		"ID": 160,
		"obj":
		{
			"EMITX1": 0.000153429,
			"EMITX2": 0.000867525,
			"RMSS1": 0.00121382,
			"RMSS2": 0.00118166
		}
		,
		"dvar":
		{
			"IBF": 372.818,
			"IM": 232.725,
			"GPHASE": -6.08273,
			"FWHM": 1.69201,
			"KQ1": -2.0315,
			"KQ2": -2.39144,
			"KQ3": 4.26087,
			"KQ4": -2.57664
		}
	}
	,
	{
		"ID": 162,
		"obj":
		{
			"EMITX1": 0.000307775,
			"EMITX2": 0.000597586,
			"RMSS1": 0.0011447,
			"RMSS2": 0.00128517
		}
		,
		"dvar":
		{
			"IBF": 357.18,
			"IM": 214.897,
			"GPHASE": -7.69535,
			"FWHM": 2.07062,
			"KQ1": -2.63568,
			"KQ2": 5.0327,
			"KQ3": 1.61431,
			"KQ4": -3.57638
		}
	}
	,
	{
		"ID": 179,
		"obj":
		{
			"EMITX1": 0.000458785,
			"EMITX2": 0.00174443,
			"RMSS1": 0.00159153,
			"RMSS2": 0.00120649
		}
		,
		"dvar":
		{
			"IBF": 404.77,
			"IM": 223.29,
			"GPHASE": -9.40541,
			"FWHM": 2.93263,
			"KQ1": 0.165867,
			"KQ2": -3.99358,
			"KQ3": -2.98349,
			"KQ4": -3.76956
		}
	}
	,
	{
		"ID": 186,
		"obj":
		{
			"EMITX1": 0.000197345,
			"EMITX2": 0.00059958,
			"RMSS1": 0.00320207,
			"RMSS2": 0.00125122
		}
		,
		"dvar":
		{
			"IBF": 418.27,
			"IM": 241.649,
			"GPHASE": -8.62743,
			"FWHM": 5.61433,
			"KQ1": -3.33143,
			"KQ2": 1.82729,
			"KQ3": -7.03274,
			"KQ4": -1.51482
		}
	}
	,
	{
		"ID": 188,
		"obj":
		{
			"EMITX1": 0.000196222,
			"EMITX2": 0.000678103,
			"RMSS1": 0.00177271,
			"RMSS2": 0.00116461
		}
		,
		"dvar":
		{
			"IBF": 270.749,
			"IM": 238.542,
			"GPHASE": -4.50056,
			"FWHM": 4.54288,
			"KQ1": -1.18595,
			"KQ2": -2.53211,
			"KQ3": 5.6094,
			"KQ4": 8.35428
		}
	}
	,
	{
		"ID": 190,
		"obj":
		{
			"EMITX1": 0.000405755,
			"EMITX2": 0.00138398,
			"RMSS1": 0.00113313,
			"RMSS2": 0.00127275
		}
		,
		"dvar":
		{
			"IBF": 309.703,
			"IM": 218.594,
			"GPHASE": -2.75893,
			"FWHM": 2.81285,
			"KQ1": 0.902073,
			"KQ2": -3.37089,
			"KQ3": -1.88567,
			"KQ4": 7.11589
		}
	}
	,
	{
		"ID": 191,
		"obj":
		{
			"EMITX1": 0.000405755,
			"EMITX2": 0.00138398,
			"RMSS1": 0.00113313,
			"RMSS2": 0.00127275
		}
		,
		"dvar":
		{
			"IBF": 309.703,
			"IM": 218.594,
			"GPHASE": -2.75893,
			"FWHM": 2.81285,
			"KQ1": 0.902073,
			"KQ2": -3.37089,
			"KQ3": -1.88567,
			"KQ4": 7.11589
		}
	}
	,
	{
		"ID": 196,
		"obj":
		{
			"EMITX1": 0.000836524,
			"EMITX2": 0.00179642,
			"RMSS1": 0.00130052,
			"RMSS2": 0.00147423
		}
		,
		"dvar":
		{
			"IBF": 443.388,
			"IM": 198.359,
			"GPHASE": -8.9899,
			"FWHM": 4.90619,
			"KQ1": 4.43519,
			"KQ2": -1.83047,
			"KQ3": -4.65909,
			"KQ4": 3.82043
		}
	}
	,
	{
		"ID": 197,
		"obj":
		{
			"EMITX1": 0.000120467,
			"EMITX2": 0.000742888,
			"RMSS1": 0.0015557,
			"RMSS2": 0.00144299
		}
		,
		"dvar":
		{
			"IBF": 239.84,
			"IM": 240.621,
			"GPHASE": -10.2479,
			"FWHM": 8.17613,
			"KQ1": -1.43827,
			"KQ2": -0.522985,
			"KQ3": -3.33792,
			"KQ4": 1.46091
		}
	}
	,
	{
		"ID": 198,
		"obj":
		{
			"EMITX1": 0.000200739,
			"EMITX2": 0.000474258,
			"RMSS1": 0.00128102,
			"RMSS2": 0.00127392
		}
		,
		"dvar":
		{
			"IBF": 221.031,
			"IM": 242.465,
			"GPHASE": -7.45472,
			"FWHM": 3.00788,
			"KQ1": -0.735819,
			"KQ2": 1.95127,
			"KQ3": -3.29379,
			"KQ4": 3.60439
		}
	}
	,
	{
		"ID": 200,
		"obj":
		{
			"EMITX1": 0.000588376,
			"EMITX2": 0.00187017,
			"RMSS1": 0.00146367,
			"RMSS2": 0.00128511
		}
		,
		"dvar":
		{
			"IBF": 342.034,
			"IM": 213.474,
			"GPHASE": -7.96503,
			"FWHM": 0.973359,
			"KQ1": -1.92562,
			"KQ2": -0.569387,
			"KQ3": 1.62968,
			"KQ4": -5.58621
		}
	}
	,
	{
		"ID": 201,
		"obj":
		{
			"EMITX1": 0.000216691,
			"EMITX2": 0.00158465,
			"RMSS1": 0.00119313,
			"RMSS2": 0.00138436
		}
		,
		"dvar":
		{
			"IBF": 396.02,
			"IM": 218.865,
			"GPHASE": -7.1707,
			"FWHM": 3.43986,
			"KQ1": -2.14832,
			"KQ2": 5.10317,
			"KQ3": 2.0933,
			"KQ4": -0.979878
		}
	}
	,
	{
		"ID": 208,
		"obj":
		{
			"EMITX1": 0.000310231,
			"EMITX2": 0.000915787,
			"RMSS1": 0.00260376,
			"RMSS2": 0.00107571
		}
		,
		"dvar":
		{
			"IBF": 505.345,
			"IM": 229.608,
			"GPHASE": -2.64165,
			"FWHM": 2.51131,
			"KQ1": 0.849289,
			"KQ2": -4.09782,
			"KQ3": -1.89254,
			"KQ4": 11.5798
		}
	}
	,
	{
		"ID": 210,
		"obj":
		{
			"EMITX1": 0.000320318,
			"EMITX2": 0.000459551,
			"RMSS1": 0.00156626,
			"RMSS2": 0.00125434
		}
		,
		"dvar":
		{
			"IBF": 286.901,
			"IM": 233.991,
			"GPHASE": 0.50304,
			"FWHM": 5.46962,
			"KQ1": 4.36633,
			"KQ2": -0.325087,
			"KQ3": 0.0823742,
			"KQ4": -3.07083
		}
	}
	,
	{
		"ID": 212,
		"obj":
		{
			"EMITX1": 0.000507649,
			"EMITX2": 0.00158291,
			"RMSS1": 0.0013907,
			"RMSS2": 0.00113215
		}
		,
		"dvar":
		{
			"IBF": 402.415,
			"IM": 223.66,
			"GPHASE": -4.29342,
			"FWHM": 2.57098,
			"KQ1": 1.31206,
			"KQ2": -5.91383,
			"KQ3": -1.7099,
			"KQ4": -4.30985
		}
	}
	,
	{
		"ID": 213,
		"obj":
		{
			"EMITX1": 0.000293582,
			"EMITX2": 0.000817877,
			"RMSS1": 0.0028495,
			"RMSS2": 0.00102586
		}
		,
		"dvar":
		{
			"IBF": 421.802,
			"IM": 228.988,
			"GPHASE": -2.69422,
			"FWHM": 3.52198,
			"KQ1": 0.744339,
			"KQ2": -5.76788,
			"KQ3": -1.20871,
			"KQ4": -5.90019
		}
	}
	,
	{
		"ID": 216,
		"obj":
		{
			"EMITX1": 0.000297831,
			"EMITX2": 0.000590316,
			"RMSS1": 0.0016257,
			"RMSS2": 0.00130374
		}
		,
		"dvar":
		{
			"IBF": 470.701,
			"IM": 239.135,
			"GPHASE": -7.93129,
			"FWHM": 5.03291,
			"KQ1": 6.45818,
			"KQ2": -1.76024,
			"KQ3": -4.65944,
			"KQ4": 2.09529
		}
	}
	,
	{
		"ID": 218,
		"obj":
		{
			"EMITX1": 0.000403098,
			"EMITX2": 0.000865439,
			"RMSS1": 0.00126949,
			"RMSS2": 0.00133889
		}
		,
		"dvar":
		{
			"IBF": 249.843,
			"IM": 221.777,
			"GPHASE": -11.7246,
			"FWHM": 3.81938,
			"KQ1": -3.1189,
			"KQ2": -3.12564,
			"KQ3": 5.44047,
			"KQ4": -6.99842
		}
	}
	,
	{
		"ID": 219,
		"obj":
		{
			"EMITX1": 0.000207214,
			"EMITX2": 0.000287997,
			"RMSS1": 0.00130782,
			"RMSS2": 0.00123529
		}
		,
		"dvar":
		{
			"IBF": 250.191,
			"IM": 237.719,
			"GPHASE": -11.8586,
			"FWHM": 4.28121,
			"KQ1": -5.9011,
			"KQ2": 0.226651,
			"KQ3": 5.63719,
			"KQ4": -6.35132
		}
	}
	,
	{
		"ID": 220,
		"obj":
		{
			"EMITX1": 0.000555805,
			"EMITX2": 0.00145619,
			"RMSS1": 0.00158557,
			"RMSS2": 0.00114597
		}
		,
		"dvar":
		{
			"IBF": 408.751,
			"IM": 225.907,
			"GPHASE": -3.83992,
			"FWHM": 4.17594,
			"KQ1": 1.58793,
			"KQ2": -5.44284,
			"KQ3": -3.38851,
			"KQ4": -3.77473
		}
	}
	,
	{
		"ID": 222,
		"obj":
		{
			"EMITX1": 0.00111907,
			"EMITX2": 0.00293513,
			"RMSS1": 0.00115994,
			"RMSS2": 0.00147617
		}
		,
		"dvar":
		{
			"IBF": 364.558,
			"IM": 231.58,
			"GPHASE": -12.0749,
			"FWHM": 2.82531,
			"KQ1": 6.92288,
			"KQ2": 0.679279,
			"KQ3": 3.57446,
			"KQ4": -2.90713
		}
	}
	,
	{
		"ID": 226,
		"obj":
		{
			"EMITX1": 0.000107985,
			"EMITX2": 0.000418042,
			"RMSS1": 0.00178323,
			"RMSS2": 0.00153743
		}
		,
		"dvar":
		{
			"IBF": 582.754,
			"IM": 229.571,
			"GPHASE": -2.46336,
			"FWHM": 8.80859,
			"KQ1": 1.15969,
			"KQ2": -2.43156,
			"KQ3": -2.90273,
			"KQ4": 5.43149
		}
	}
	,
	{
		"ID": 232,
		"obj":
		{
			"EMITX1": 0.000298133,
			"EMITX2": 0.00148242,
			"RMSS1": 0.00123736,
			"RMSS2": 0.00132291
		}
		,
		"dvar":
		{
			"IBF": 433.025,
			"IM": 217.804,
			"GPHASE": -6.73076,
			"FWHM": 3.29082,
			"KQ1": -2.096,
			"KQ2": -2.20754,
			"KQ3": 2.87752,
			"KQ4": 0.595402
		}
	}
	]
}
